Workbook
Name Aporte: App!$D$15
Name patrimonio: App!$D$18
Name QTDE_Anos: App!$D$16
Name Rendimento_carteira: App!$D$11
Name salario: App!$D$10
Name sugestao_investimento: App!$B$12
Name taxa_mensal: App!$D$17
Name taxa_rendimento_mensal: App!$B$17

Sheet App
B9: CONFIGURAÇÕES
B10: Salário | D10: 4200
B11: Rendimento Carteira | D11: 0.006
B12: Sugestão de Investimento (30%) | D12: =salario*30% -> 1260
B14: INVESTIMENTO MENSAL
B15: Quanto investir por mês? | D15: =D12 -> 1260
B16: Por quantos anos? | D16: 5
B17: Taxa de rendimento mensal? | D17: 0.01079
B18: Patrimônio acumulado? | D18: =FV(taxa_mensal,QTDE_Anos*12,Aporte)*-1 -> 105558.91
B19: Dividendos mensais? | D19: =patrimonio*Rendimento_carteira -> 633.35347
B21: CENÁRIOS | D21: Dividendo
A22: 2 | B22: Quanto em 2 anos? | C22: =FV($D$17,$A22*12,Aporte*-1) -> 34306.81 | D22: =C22*Rendimento_carteira -> 205.84086
A23: 5 | B23: Quanto em 5 anos? | C23: =FV($D$17,$A23*12,$D$15*-1) -> 105558.91 | D23: =C23*Rendimento_carteira -> 633.35347
A24: 10 | B24: Quanto em 10 anos? | C24: =FV($D$17,$A24*12,$D$15*-1) -> 306538.11 | D24: =C24*Rendimento_carteira -> 1839.2286
A25: 20 | B25: Quanto em 20 anos? | C25: =FV($D$17,$A25*12,$D$15*-1) -> 1417750 | D25: =C25*Rendimento_carteira -> 8506.4999
A26: 30 | B26: Quanto em 30 anos? | C26: =FV($D$17,$A26*12,$D$15*-1) -> 5445933.8 | D26: =C26*Rendimento_carteira -> 32675.603
B30: PERFIL | C30: Moderado
B31: VALOR A SER INVESTIDO POR MÊS | C31: =Aporte -> 1260
B33: TIPO DE FII | C33: Percentual Sugerido | D33: Valores
B34: PAPEL | C34: =VLOOKUP($C$30&"-"&B34,Planilha2!$A$1:$D$20,4,FALSE) -> 0.32 | D34: =C34*$C$31 -> 403.2
B35: TIJOLO | C35: =VLOOKUP($C$30&"-"&B35,Planilha2!$A$1:$D$20,4,FALSE) -> 0.35 | D35: =C35*$C$31 -> 441
B36: HÍBRIDOS | C36: =VLOOKUP($C$30&"-"&B36,Planilha2!$A$1:$D$20,4,FALSE) -> 0.08 | D36: =C36*$C$31 -> 100.8
B37: FOFs | C37: =VLOOKUP($C$30&"-"&B37,Planilha2!$A$1:$D$20,4,FALSE) -> 0.05 | D37: =C37*$C$31 -> 63
B38: DESENVOLVIMENTO | C38: =VLOOKUP($C$30&"-"&B38,Planilha2!$A$1:$D$20,4,FALSE) -> 0.1 | D38: =C38*$C$31 -> 126
B39: HOTELARIAS | C39: =VLOOKUP($C$30&"-"&B39,Planilha2!$A$1:$D$20,4,FALSE) -> 0.1 | D39: =C39*$C$31 -> 126
D40: =SUM(D34:D39) -> 1260

Sheet Planilha2
A2: Chave | B2: PERFIL | C2: TIPO DE FII | D2: %
A3: =B3&"-"&C3 -> Conservador-PAPEL | B3: Conservador | C3: PAPEL | D3: 0.3
A4: =B4&"-"&C4 -> Conservador-TIJOLO | B4: Conservador | C4: TIJOLO | D4: 0.5
A5: =B5&"-"&C5 -> Conservador-HÍBRIDOS | B5: Conservador | C5: HÍBRIDOS | D5: 0.1 | G5: =A10 -> Moderado-TIJOLO | H5: =VLOOKUP($G$5,$A:$D,4,FALSE) -> 0.35
A6: =B6&"-"&C6 -> Conservador-FOFs | B6: Conservador | C6: FOFs | D6: 0.1
A7: =B7&"-"&C7 -> Conservador-DESENVOLVIMENTO | B7: Conservador | C7: DESENVOLVIMENTO | D7: 0
A8: =B8&"-"&C8 -> Conservador-HOTELARIAS | B8: Conservador | C8: HOTELARIAS | D8: 0
A9: =B9&"-"&C9 -> Moderado-PAPEL | B9: Moderado | C9: PAPEL | D9: 0.32
A10: =B10&"-"&C10 -> Moderado-TIJOLO | B10: Moderado | C10: TIJOLO | D10: 0.35
A11: =B11&"-"&C11 -> Moderado-HÍBRIDOS | B11: Moderado | C11: HÍBRIDOS | D11: 0.08
A12: =B12&"-"&C12 -> Moderado-FOFs | B12: Moderado | C12: FOFs | D12: 0.05
A13: =B13&"-"&C13 -> Moderado-DESENVOLVIMENTO | B13: Moderado | C13: DESENVOLVIMENTO | D13: 0.1
A14: =B14&"-"&C14 -> Moderado-HOTELARIAS | B14: Moderado | C14: HOTELARIAS | D14: 0.1
A15: =B15&"-"&C15 -> Agressivo-PAPEL | B15: Agressivo | C15: PAPEL | D15: 0.5
A16: =B16&"-"&C16 -> Agressivo-TIJOLO | B16: Agressivo | C16: TIJOLO | D16: 0.1
A17: =B17&"-"&C17 -> Agressivo-HÍBRIDOS | B17: Agressivo | C17: HÍBRIDOS | D17: 0.05
... A20: =B20&"-"&C20 -> Agressivo-HOTELARIAS | B20: Agressivo | C20: HOTELARIAS | D20: 0.1
